torchverif/__init__.py
torchverif/interval_tensor/__init__.py
torchverif/interval_tensor/v1/__init__.py
torchverif/interval_tensor/v2/__init__.py
torchverif/net_interval/__init__.py
torchverif/net_interval/v1/__init__.py
torchverif/net_interval/v2/__init__.py
torchverif/pvs/__init__.py
torchverif/pvs/torch2pvs.py
torchverif/smc/__init__.py
torchverif/smc/plot_helper.py
torchverif-0.0.2.dist-info/METADATA
torchverif-0.0.2.dist-info/WHEEL
torchverif-0.0.2.dist-info/licenses/LICENSE
torchverif-0.0.2.dist-info/RECORD
